asynctkinter2/__init__.py
asynctkinter2/_tkinter_stuff.py
asynctkinter2-0.1.0.dist-info/WHEEL
asynctkinter2-0.1.0.dist-info/METADATA
asynctkinter2-0.1.0.dist-info/RECORD
