Metadata-Version: 2.4
Name: asynctkinter2
Version: 0.1.0
Summary: Async library for Tkinter
Keywords: async,tkinter
Author: Nattōsai Mitō
Author-email: Nattōsai Mitō <flow4re2c@gmail.com>
License-Expression: MIT
Classifier: Development Status :: 5 - Production/Stable
Classifier: License :: OSI Approved :: MIT License
Classifier: Intended Audience :: Developers
Classifier: Programming Language :: Python
Classifier: Programming Language :: Python :: 3.10
Classifier: Programming Language :: Python :: 3.11
Classifier: Programming Language :: Python :: 3.12
Classifier: Programming Language :: Python :: 3.13
Classifier: Programming Language :: Python :: 3.14
Classifier: Topic :: Software Development :: Libraries
Classifier: Operating System :: OS Independent
Requires-Dist: asyncgui>=0.9.3,<0.11
Requires-Python: >=3.10, <4.0
Project-URL: Repository, https://github.com/asyncgui/asynctkinter2
